{"query": {"count": 1, "lang": "en-US", "diagnostics": {"url": {"content": "http://weather.yahooapis.com/forecastrss?w=12703515", "execution-stop-time": "5", "execution-start-time": "0", "execution-time": "5"}, "user-time": "5", "build-version": "0.2.1867", "service-time": "5", "publiclyCallable": "true"}, "results": {"channel": {"lastBuildDate": "Tue, 29 Oct 2013 9:30 am CST", "atmosphere": {"pressure": "30.12", "rising": "0", "visibility": "6.21", "humidity": "51"}, "description": "Yahoo! Weather for Taipei City, TW", "language": "en-us", "title": "Yahoo! Weather - Taipei City, TW", "image": {"url": "http://l.yimg.com/a/i/brand/purplelogo//uh/us/news-wea.gif", "width": "142", "height": "18", "link": "http://weather.yahoo.com", "title": "Yahoo! Weather"}, "item": {"description": "\n<img src=\"http://l.yimg.com/a/i/us/we/52/30.gif\"/><br />\n<b>Current Conditions:</b><br />\nPartly Cloudy, 79 F<BR />\n<BR /><b>Forecast:</b><BR />\nTue - Sunny. High: 80 Low: 71<br />\nWed - Partly Cloudy/Wind. High: 82 Low: 72<br />\nThu - Mostly Cloudy. High: 81 Low: 73<br />\nFri - Scattered Thunderstorms. High: 80 Low: 74<br />\nSat - Isolated Thunderstorms. High: 84 Low: 75<br />\n<br />\n<a href=\"http://us.rd.yahoo.com/dailynews/rss/weather/Taipei_City__TW/*http://weather.yahoo.com/forecast/TWXX0022_f.html\">Full Forecast at Yahoo! Weather</a><BR/><BR/>\n(provided by <a href=\"http://www.weather.com\" >The Weather Channel</a>)<br/>\n", "pubDate": "Tue, 29 Oct 2013 9:30 am CST", "title": "Conditions for Taipei City, TW at 9:30 am CST", "long": "121.51", "forecast": [{"code": "32", "text": "Sunny", "high": "80", "low": "71", "date": "29 Oct 2013", "day": "Tue"}, {"code": "24", "text": "Partly Cloudy/Wind", "high": "82", "low": "72", "date": "30 Oct 2013", "day": "Wed"}, {"code": "28", "text": "Mostly Cloudy", "high": "81", "low": "73", "date": "31 Oct 2013", "day": "Thu"}, {"code": "38", "text": "Scattered Thunderstorms", "high": "80", "low": "74", "date": "1 Nov 2013", "day": "Fri"}, {"code": "37", "text": "Isolated Thunderstorms", "high": "84", "low": "75", "date": "2 Nov 2013", "day": "Sat"}], "link": "http://us.rd.yahoo.com/dailynews/rss/weather/Taipei_City__TW/*http://weather.yahoo.com/forecast/TWXX0022_f.html", "lat": "25.04", "guid": {"isPermaLink": "false", "content": "TWXX0022_2013_11_02_7_00_CST"}, "condition": {"date": "Tue, 29 Oct 2013 9:30 am CST", "text": "Partly Cloudy", "code": "30", "temp": "79"}}, "link": "http://us.rd.yahoo.com/dailynews/rss/weather/Taipei_City__TW/*http://weather.yahoo.com/forecast/TWXX0022_f.html", "location": {"city": "Taipei City", "region": "", "country": "Taiwan"}, "ttl": "60", "units": {"distance": "mi", "speed": "mph", "temperature": "F", "pressure": "in"}, "astronomy": {"sunset": "5:15 pm", "sunrise": "5:59 am"}, "wind": {"direction": "90", "speed": "13", "chill": "79"}}}, "created": "2013-10-29T02:03:47Z"}}